{
  "http://": {
    "types": {
      "JPEG": [
        "/snapshot.cgi?user=[USERNAME]&pwd=[PASSWORD]&count=0",
        "/cgi/snapshot.cgi?action=getdata&channel.[CHANNEL].capture=true&channel.[CHANNEL].resolution=1",
        "/snapshot.cgi?usr=[USERNAME]&pwd=[PASSWORD]",
        "/snapshot.cgi?user=[USERNAME]&pwd=[PASSWORD]"
      ],
      "MJPEG": [
        "/videostream.cgi",
        "/videostream.cgi?",
        "/videostream.cgi?rate=0&user=[USERNAME]&pwd=[PASSWORD]"
      ],
      "FFMPEG": [
        "/videostream.asf",
        "/videostream.asf?user=[USERNAME]&pwd=[PASSWORD]&resolution=[WIDTH]x[HEIGHT]",
        "/videostream.cgi?resolution=8&rate=13"
      ]
    },
    "models": [
      "C601",
      "C602",
      "C801",
      "C802",
      "OTHER",
      "P2PC602"
    ]
  }
}
