{
  "http://": {
    "types": {
      "MJPEG": {
        "/videofeed": [],
        "/video": [
          "submenu=mjpg",
          "profile=[CHANNEL]"
        ],
        "/video.mjpg": []
      },
      "JPEG": {
        "/snapshot/view[CHANNEL].jpg": []
      }
    },
    "models": [
      "ASCENDQ",
      "G300",
      "G740",
      "IMPULSE4G",
      "MEDIAPAD",
      "PHONE",
      "U9200",
      "Y220",
      "Y320",
      "Y511"
    ]
  },
  "rtsp://": {
    "types": {
      "H.264": {
        "/Streaming/Channels/1": []
      }
    },
    "models": [
      "IPC6331-IR"
    ]
  }
}
