{
  "http://": {
    "types": {
      "JPEG": [
        "/tmpfs/auto.jpg",
        "/cgi/snapshot.cgi?action=getdata&channel.[CHANNEL].capture=true&channel.[CHANNEL].resolution=1",
        "/snapshot.cgi?user=[USERNAME]&pwd=[PASSWORD]&count=0",
        "/snapshot.cgi?user=[USERNAME]&pwd=[PASSWORD]",
        "/snapshot.cgi?camera=[CHANNEL]",
        "/snapshot.cgi?usr=[USERNAME]&pwd=[PASSWORD]",
        "/snapshot.cgi",
        "/img/snapshot.cgi?img=vga",
        "/img/snapshot.cgi?size=2",
        "/img/snapshot.cgi?size=3"
      ],
      "MJPEG": [
        "/videostream.cgi?user=[USERNAME]&pwd=[PASSWORD]&resolution=32&rate=0",
        "/videostream.cgi?rate=0&user=[USERNAME]&pwd=[PASSWORD]",
        "/videostream.cgi",
        "/videostream.cgi?user=[USERNAME]&pwd=[PASSWORD]&resolution=32",
        "/videostream.cgi?user=[USERNAME]&password=[PASSWORD]",
        "/videostream.cgi?usr=[USERNAME]&pwd=[PASSWORD]",
        "/videostream.cgi?rate=11",
        "/videostream.cgi?user=[USERNAME]&pwd=[PASSWORD]",
        "/videostream.cgi?rate=0",
        "/mjpeg.cgi?user=[USERNAME]&password=[PASSWORD]&channel=[CHANNEL]"
      ],
      "H.264": [
        "/videostream.asf?usr=[USERNAME]&pwd=[PASSWORD]",
        "/videostream.asf",
        "/videostream.asf?user=[USERNAME]&pwd=[PASSWORD]&resolution=[WIDTH]*[HEIGHT]",
        "/videostream.cgi?resolution=8&rate=13"
      ]
    },
    "models": [
      "0001",
      "003",
      "004",
      "004964",
      "013",
      "A0009",
      "A001",
      "A003",
      "A006",
      "AABEC",
      "AAP003",
      "AJ-C2WA-C118",
      "AP008",
      "APSERIESIPCAMERS",
      "AP0005",
      "AP0009",
      "AP001",
      "AP-001",
      "AP002",
      "AP003",
      "AP-003",
      "AP003(WORKING)",
      "AP003B",
      "AP-004",
      "AP-005",
      "AP006",
      "AP-006",
      "AP007",
      "AP-008",
      "AP009",
      "AP-009",
      "AP009TESTED",
      "AP-011",
      "AP-012",
      "AP03",
      "AP05",
      "AP1",
      "AP995",
      "AP-CAM",
      "CAM1",
      "CTO185",
      "FRANK-IPCAM",
      "FRANKIPCAM",
      "FRONTDOOR",
      "H.264",
      "HOME",
      "KILINSKIAPCAM",
      "MY0210-IPCAM",
      "OTHER",
      "P2P-BLACK",
      "P2PBLACK(FRANK)",
      "PTZ",
      "SP005",
      "SP008",
      "SP-008",
      "SP009",
      "SP011",
      "SP012",
      "SP013",
      "SP015",
      "SP004",
      "SP006",
      "SP014",
      "WIFIAP",
      "006",
      "1",
      "VIEW-004964-CTETZ"
    ]
  },
  "rtsp://": {
    "types": {
      "H.264": [
        "/11",
        "/ucast/11",
        "/onvif1",
        "/onvif2",
        "/ucast/12",
        "/rtsp_live1"
      ]
    },
    "models": [
      "485906",
      "AAP003",
      "AP001",
      "AP002",
      "AP003",
      "AP003(WORKING)",
      "AP-005",
      "AP-005KITCHEN",
      "AP-006",
      "AP006C",
      "AP-008",
      "AP-009",
      "AP015",
      "BV852",
      "DOME",
      "FLOUREON",
      "INNECAM",
      "IPC",
      "IPC_441311SP_15",
      "IPC_748484",
      "IPC_794113",
      "IPC_807757",
      "IPC_819175",
      "IPC_830435",
      "ONIF",
      "ONVIFSP013",
      "OTHER",
      "OTHER(MYIPCAM)",
      "PANTILT",
      "PTZ",
      "PTZIP008",
      "SP0009A",
      "SP-002",
      "SP005",
      "SP005DG",
      "SP008",
      "SP-008",
      "SP009A",
      "SP009C",
      "SP012",
      "SP013",
      "SP014",
      "SP015",
      "SP015_AK",
      "SP017",
      "SP07",
      "SP09",
      "SP12",
      "SP14",
      "SQLODGE"
    ]
  }
}
